{"data":{"site":{"siteMetadata":{"title":"bono's blog","author":"bono"}},"markdownRemark":{"id":"0cf0755b-c8ad-56bb-a829-b1241fa3c02e","excerpt":"","html":"","frontmatter":{"title":"","date":null}}},"pageContext":{"slug":"/python-import-by-class-name/","previous":{"fields":{"slug":"/django-setting-for-pycharm-community/"},"frontmatter":{"title":"[django] pycharm(파이참) community 버전으로 django(장고) 프로젝트 설정"}},"next":{"fields":{"slug":"/python-about-set/"},"frontmatter":{"title":"[python] set에 관한 두가지 사실"}}}}